LICENSE
MANIFEST.in
README.rst
RELEASE-VERSION
setup.cfg
setup.py
docs/overview.rst
docs/scc.rst
docs/toc.rst
docs/tutorial.rst
examples/bandwidth.py
examples/blockstore_report.py
examples/connection_history_report.py
examples/initiator_io_report.py
examples/lun_io_report.py
examples/multi_dev_reports.py
examples/network_io_report.py
examples/qos_report.py
examples/reg_peak_traffic_reports.py
examples/single_dev_reports.py
examples/snap_mirror_report.py
examples/throughput.py
gitpy_versioning/__init__.py
steelscript/__init__.py
steelscript.scc.egg-info/PKG-INFO
steelscript.scc.egg-info/SOURCES.txt
steelscript.scc.egg-info/dependency_links.txt
steelscript.scc.egg-info/entry_points.txt
steelscript.scc.egg-info/namespace_packages.txt
steelscript.scc.egg-info/requires.txt
steelscript.scc.egg-info/top_level.txt
steelscript/scc/__init__.py
steelscript/scc/appfwk/__init__.py
steelscript/scc/appfwk/plugin.py
steelscript/scc/appfwk/datasources/__init__.py
steelscript/scc/appfwk/datasources/scc.py
steelscript/scc/appfwk/devices/__init__.py
steelscript/scc/appfwk/devices/scc.py
steelscript/scc/appfwk/reports/__init__.py
steelscript/scc/appfwk/reports/appliance_report.py
steelscript/scc/appfwk/reports/throughput_report.py
steelscript/scc/core/__init__.py
steelscript/scc/core/app.py
steelscript/scc/core/report.py
steelscript/scc/core/scc.py
steelscript/scc/core/servicedef/cmc.appliance_inventory.yml
steelscript/scc/core/servicedef/cmc.stats.yml