Metadata-Version: 2.1
Name: steelscript.scc
Version: 2.0
Summary: SteelScript support for SteelCentral Controller
Home-page: http://pythonhosted.org/steelscript
Author: Riverbed Technology
Author-email: eng-github@riverbed.com
License: MIT
Platform: Linux
Platform: Mac OS
Platform: Windows
Classifier: Development Status :: 4 - Beta
Classifier: Intended Audience :: Developers
Classifier: Intended Audience :: Information Technology
Classifier: Intended Audience :: System Administrators
Classifier: License :: OSI Approved :: MIT License
Classifier: Programming Language :: Python :: 3.5
Classifier: Topic :: System :: Networking
Provides-Extra: dev
Provides-Extra: test
Provides-Extra: all
Provides-Extra: doc
